{
  "glossary": {
    "title": "उदाहरण के शब्दकोष",
    "GlossDiv": {
      "title": "एस",
      "GlossList": {
        "GlossEntry": {
          "ID": "SGML",
          "SortAs": "SGML",
          "GlossTerm": "स्टैंडर्ड सामान्यीकृत मार्कअप लैंग्वेज",
          "Acronym": "SGML",
          "Abbrev": "आईएसओ 8879: 1986",
          "GlossDef": {
            "para": "एक मेटा-मार्कअप भाषा, ऐसे DocBook के रूप में मार्कअप भाषाओं को बनाने के लिए इस्तेमाल किया।",
            "GlossSeeAlso": [
              "GML",
              "एक्सएमएल"]
            
          },
          "GlossSee": "मार्कअप"
        }
      }
    }
  }
}
